Metadata-Version: 2.1
Name: setvaluedprediction
Version: 0.0.6
Summary: Set-valued predictors in Python
Home-page: https://github.com/tfmortie/setvaluedprediction
Author: Thomas Mortier
Author-email: thomas.mortier92@gmail.com
License: MIT license
Platform: UNKNOWN
License-File: LICENSE
